prefect_invenio_rdm/__init__.py
prefect_invenio_rdm/constants.py
prefect_invenio_rdm/credentials.py
prefect_invenio_rdm/flows.py
prefect_invenio_rdm/tasks.py
prefect_invenio_rdm/test.py
prefect_invenio_rdm/models/__init__.py
prefect_invenio_rdm/models/api.py
prefect_invenio_rdm/models/records.py
prefect_invenio_rdm-0.0.6.dist-info/METADATA
prefect_invenio_rdm-0.0.6.dist-info/WHEEL
prefect_invenio_rdm-0.0.6.dist-info/entry_points.txt
prefect_invenio_rdm-0.0.6.dist-info/top_level.txt
prefect_invenio_rdm-0.0.6.dist-info/RECORD
