Metadata-Version: 2.4
Name: prefect-invenio-rdm
Version: 0.0.6
Summary: Prefect integrations interacting with an InvenioRDM instance.
Author-email: Joel Goncalves <goncalves.joel95@gmail.com>, "ARISA LAB, LLC" <admin@ARISALab.org>
License: MIT
Project-URL: Homepage, https://github.com/ARISA-Lab-LLC/prefect-invenio-rdm
Keywords: prefect,invenio,invenio-rdm
Classifier: Natural Language :: English
Classifier: Intended Audience :: Developers
Classifier: License :: OSI Approved :: MIT License
Classifier: Programming Language :: Python :: 3 :: Only
Classifier: Programming Language :: Python :: 3.9
Classifier: Programming Language :: Python :: 3.10
Classifier: Programming Language :: Python :: 3.11
Classifier: Programming Language :: Python :: 3.12
Classifier: Topic :: Software Development :: Libraries
Requires-Python: >=3.9
Requires-Dist: prefect>=3.0.0
Provides-Extra: dev
Requires-Dist: coverage; extra == "dev"
Requires-Dist: pytest-asyncio; extra == "dev"
Requires-Dist: pytest>=8.3; extra == "dev"
Requires-Dist: pytest-env; extra == "dev"
Requires-Dist: pytest-xdist; extra == "dev"
Requires-Dist: pytest-mock; extra == "dev"
Requires-Dist: respx; extra == "dev"
